{
  "consoleStringGoal": "5",
  "kuriGoalString": "Set the array in numerical order",
  "varNames": [ "Var1" ],
  "initialVariableValues": [ 0 ],
  "finalVariableGoalValues": [ [ 1, 2, 3 ] ],
  "exerciseBlocks": {
    "$type": "MoveToCode.Pair[], Assembly-CSharp",
    "$values": [
      {
        "codeBlockID": "Print"
      },
      {
        "codeBlockID": "SetVar"
      },
      {
        "codeBlockID": "Array"
      },
      {
        "codeBlockID": "Int",
        "value": 1
      },
      {
        "codeBlockID": "Int",
        "value": 2
      },
      {
        "codeBlockID": "Int",
        "value": 3
      }
    ]
  },
  "scaffoldDialogue": [
    "You don't need to use all of the blocks",
    "You can use math blocks inside of math blocks",
    "Order of operations matters"
  ]
}